{
	"Type": "Card",
	"GUID": "2EBF5850447848C218D3C8A6ED37EB13",
	"Name": "ADSET Cards",
	"Metadata": "",
	"CollisionType": "Regular",
	"Friction": 0.7,
	"Restitution": 0,
	"Density": 0.5,
	"SurfaceType": "Cardboard",
	"Roughness": 1,
	"Metallic": 0,
	"PrimaryColor":
	{
		"R": 255,
		"G": 255,
		"B": 255
	},
	"SecondaryColor":
	{
		"R": 0,
		"G": 0,
		"B": 0
	},
	"Flippable": true,
	"AutoStraighten": false,
	"ShouldSnap": true,
	"ScriptName": "",
	"Blueprint": "",
	"Models": [],
	"Collision": [],
	"SnapPointsGlobal": false,
	"SnapPoints": [],
	"ZoomViewDirection":
	{
		"X": 0,
		"Y": 0,
		"Z": 0
	},
	"Tags": [],
	"FrontTexture": "ADSET_Cards_Text.png",
	"BackTexture": "ADSET_CardBack.png",
	"HiddenTexture": "",
	"BackIndex": -2,
	"HiddenIndex": -1,
	"NumHorizontal": 6,
	"NumVertical": 2,
	"Width": 6.35,
	"Height": 8.89,
	"Thickness": 0.05,
	"HiddenInHand": true,
	"UsedWithCardHolders": true,
	"CanStack": true,
	"UsePrimaryColorForSide": false,
	"FrontTextureOverrideExposed": false,
	"AllowFlippedInStack": false,
	"MirrorBack": true,
	"EmissiveFront": false,
	"Model": "Rounded",
	"Indices": [ 0, 1, 2, 3, 4, 5, 6, 7, 8, 9, 10 ],
	"CardNames":
	{
	},
	"CardMetadata":
	{
	},
	"CardTags":
	{
	}
}